README.md
setup.cfg
setup.py
Baubles/Colours.py
Baubles/LogColour.py
Baubles/Logger.py
Baubles/__init__.py
Baubles.egg-info/PKG-INFO
Baubles.egg-info/SOURCES.txt
Baubles.egg-info/dependency_links.txt
Baubles.egg-info/top_level.txt