Metadata-Version: 2.1
Name: Baubles
Version: 1.6
Summary: UNKNOWN
Home-page: https://github.com/eddo888/baubles
Author: David Edson
Author-email: eddo888@tpg.com.au
License: MIT
Download-URL: https://github.com/eddo888/baubles/archive/1.6.tar.gz
Platform: UNKNOWN
